graphbit/__init__.py
graphbit/graphbit.cp310-win_amd64.pyd
graphbit_python-0.4.0.dist-info/METADATA
graphbit_python-0.4.0.dist-info/WHEEL
graphbit_python-0.4.0.dist-info/RECORD
