Metadata-Version: 2.4
Name: graphbit-python
Version: 0.4.0
Summary: Production-grade Python bindings for GraphBit agentic workflow automation
Keywords: ai,automation,workflow,agent,llm
Home-Page: https://graphbit.ai
Author: GraphBit Team
Project-URL: Source Code, https://github.com/InfinitiBit/graphbit
